[
    { "name" : "muslim",
      "singular" : "muslim",
      "plural" : "muslims",
      "changes_name" : true,
      "changes_last_name" : true,
      "religious_percent" : 80 },
    { "name" : "buddhist",
      "singular" : "buddhist",
      "plural" : "buddhists",
      "changes_name" : false,
      "changes_last_name" : false,
      "religious_percent" : 40 },
    { "name" : "catholic",
      "singular" : "catholic",
      "plural" : "catholics",
      "changes_name" : false,
      "changes_last_name" : false,
      "religious_percent" : 50 },
    { "name" : "protestant",
      "singular" : "protestant",
      "plural" : "protestants",
      "changes_name" : true,
      "changes_last_name" : false,
      "religious_percent" : 20 },
    { "name" : "jewish",
      "singular" : "jew",
      "plural" : "jews",
      "changes_name" : true,
      "changes_last_name" : false,
      "religious_percent" : 60 },
    { "name" : "hindu",
      "singular" : "hindu",
      "plural" : "hindus",
      "changes_name" : false,
      "changes_last_name" : false,
      "religious_percent" : 70 }
]